ovos_skill_count/__init__.py
ovos_skill_count/version.py
ovos_skill_count/locale/en-us/cardinal.voc
ovos_skill_count/locale/en-us/count_to_N.error.dialog
ovos_skill_count/locale/en-us/count_to_N.intent
ovos_skill_count/locale/en-us/failed_extract_number.dialog
ovos_skill_count/locale/en-us/infinity.voc
ovos_skill_count/locale/en-us/long_scale.voc
ovos_skill_count/locale/en-us/ordinal.voc
ovos_skill_count/locale/en-us/short_scale.voc
ovos_skill_count/locale/pt-pt/cardinal.voc
ovos_skill_count/locale/pt-pt/count_to_N.intent
ovos_skill_count/locale/pt-pt/failed_extract_number.dialog
ovos_skill_count/locale/pt-pt/infinity.voc
ovos_skill_count/locale/pt-pt/long_scale.voc
ovos_skill_count/locale/pt-pt/ordinal.voc
ovos_skill_count/locale/pt-pt/short_scale.voc
ovos_skill_count-0.0.2.dist-info/LICENSE
ovos_skill_count-0.0.2.dist-info/METADATA
ovos_skill_count-0.0.2.dist-info/WHEEL
ovos_skill_count-0.0.2.dist-info/entry_points.txt
ovos_skill_count-0.0.2.dist-info/top_level.txt
ovos_skill_count-0.0.2.dist-info/RECORD
