Metadata-Version: 2.1
Name: ovos-skill-count
Version: 0.0.2
Summary: OVOS count to N skill
Home-page: https://github.com/OpenVoiceOS/ovos-skill-count
Author: OpenVoiceOS
Author-email: jarbasai@mailfence.com
License: Apache-2.0
Keywords: ovos skill plugin
License-File: LICENSE
